cc_net_prepro.py
doc_Gopher_statistics.py
doc_c4_statistics.py
doc_quality_local.py
doc_quality_local_python.py
doc_quality_transform.py
doc_quality_transform_python.py
doc_quality_utils.py
dpk_doc_quality_transform_python-0.2.1.dist-info/METADATA
dpk_doc_quality_transform_python-0.2.1.dist-info/WHEEL
dpk_doc_quality_transform_python-0.2.1.dist-info/top_level.txt
dpk_doc_quality_transform_python-0.2.1.dist-info/RECORD
